{
  "msg": "获取用户信息成功",
  "result": 0,
  "code": 0,
  "data": {
    "amountNum": "",
    "photoPath": "http://images.mizholdings.com/img_default.png",
    "userPhone": "",
    "classroomId": "",
    "privateCharge": 1,
    "userIdentity": 0,
    "orgMsgList": [],
    "teacherCount": 0,
    "linkName": "",
    "subjectId": 0,
    "recommandId": 0,
    "billsum": 0,
    "orgType": 0,
    "starTeacher": 0,
    "password": "123",
    "context": "",
    "taxpayerNum": "",
    "billBank": "",
    "mizhuTime": 30.0,
    "bankAccount": "",
    "qq": "",
    "friendCount": 0,
    "mizhuCoin": 0.0,
    "orgName": "",
    "unionId": "",
    "publicCharge": 0,
    "studentScore": 3,
    "editionId": 0,
    "agentName": "",
    "courseList": [],
    "integ": 105,
    "relPhone": "",
    "authenResult": 0,
    "loginMode": 1,
    "billName": "",
    "userTypeValue": "学生",
    "cloudUsrId": "19748e2867202289719a1c3255cd67ea",
    "billPhone": "",
    "cardId": "",
    "collectionCount": 0,
    "name": "",
    "pharseId": 0,
    "userType": 3,
    "cloudUsrAccount": "ac5d92b37dd14a42a5444e9c6f22d028",
    "phaseName": "",
    "status": 1,
    "birthday": "",
    "studentCount": 0,
    "agentId": 0,
    "loginType": 0,
    "openId": "",
    "canAdd": 0,
    "className": "",
    "coursewareCount": 0,
    "orgRelList": [],
    "recommend": 0,
    "roomCode": "",
    "orgId": 0,
    "userCode": "1AQMKOSLKJ4",
    "times": 0,
    "loginTime": 0,
    "cityName": "",
    "top": 0,
    "userIdentityValue": "个人",
    "friendInteg": 0.0,
    "mizhuFrozen": 0.0,
    "userIds": [],
    "nickname": "mizhu1714",
    "mySign": "",
    "department": "",
    "lessonList": [],
    "regAddress": "",
    "email": "",
    "regChannel": 0,
    "subjectName": "",
    "summary": "",
    "gradeName": "",
    "gradeId": 0,
    "address": "",
    "booktoken": "EQ_4746875930823680",
    "editionName": "",
    "sex": "-",
    "userKeep": 0,
    "userId": 4746875930823680,
    "token": "17E59E01-7188-4E12-AEB9-0F849DAF9ED2",
    "lessonCount": 0,
    "createTime": "2020-01-09 17:14:48",
    "creditNum": 0,
    "userOrgList": [],
    "authenStatus": "已认证",
    "authen": 3,
    "payPassword": "",
    "account": "renzhengzhuanyong",
    "age": 0
  }